costflow/__init__.py
costflow/analyzer.py
costflow/cli.py
costflow/fitting.py
costflow/models.py
costflow/report.py
costflow/tracing.py
costflow/utils.py
costflow-0.1.3.dist-info/licenses/LICENSE
costflow-0.1.3.dist-info/METADATA
costflow-0.1.3.dist-info/WHEEL
costflow-0.1.3.dist-info/entry_points.txt
costflow-0.1.3.dist-info/top_level.txt
costflow-0.1.3.dist-info/RECORD
