Metadata-Version: 2.4
Name: costflow
Version: 0.1.3
Summary: Cost estimation & scaling analysis for pandas pipelines
Author: Shradhit Subudhi
License: MIT
Project-URL: Homepage, https://github.com/shradhit/costflow
Project-URL: Repository, https://github.com/shradhit/costflow
Keywords: pandas,performance,profiling,scaling,analytics
Classifier: Development Status :: 3 - Alpha
Classifier: Intended Audience :: Science/Research
Classifier: License :: OSI Approved :: MIT License
Classifier: Programming Language :: Python :: 3
Classifier: Programming Language :: Python :: 3 :: Only
Classifier: Programming Language :: Python :: 3.10
Classifier: Programming Language :: Python :: 3.11
Classifier: Programming Language :: Python :: 3.12
Classifier: Topic :: Scientific/Engineering :: Information Analysis
Requires-Python: >=3.10
License-File: LICENSE
Requires-Dist: numpy>=1.24
Requires-Dist: pandas>=2.0
Provides-Extra: mem
Requires-Dist: psutil>=5.9; extra == "mem"
Provides-Extra: dev
Requires-Dist: pytest>=7; extra == "dev"
Requires-Dist: ruff>=0.4; extra == "dev"
Provides-Extra: docs
Requires-Dist: mkdocs>=1.5; extra == "docs"
Dynamic: license-file
